vc2_pseudocode_parser/__init__.py
vc2_pseudocode_parser/docx_generator.py
vc2_pseudocode_parser/docx_transformer.py
vc2_pseudocode_parser/py.typed
vc2_pseudocode_parser/python_transformer.py
vc2_pseudocode_parser/version.py
vc2_pseudocode_parser/parser/__init__.py
vc2_pseudocode_parser/parser/ast.py
vc2_pseudocode_parser/parser/grammar.peg
vc2_pseudocode_parser/parser/grammar.py
vc2_pseudocode_parser/parser/operators.py
vc2_pseudocode_parser/parser/parser.py
vc2_pseudocode_parser/scripts/__init__.py
vc2_pseudocode_parser/scripts/vc2_pseudocode_to_docx.py
vc2_pseudocode_parser/scripts/vc2_pseudocode_to_python.py
vc2_pseudocode_parser-1.0.0.dist-info/LICENSE.txt
vc2_pseudocode_parser-1.0.0.dist-info/METADATA
vc2_pseudocode_parser-1.0.0.dist-info/WHEEL
vc2_pseudocode_parser-1.0.0.dist-info/entry_points.txt
vc2_pseudocode_parser-1.0.0.dist-info/top_level.txt
vc2_pseudocode_parser-1.0.0.dist-info/RECORD
