Metadata-Version: 2.1
Name: vc2-pseudocode-parser
Version: 1.0.0
Summary: Parser and translator for the pseudocode language used in SMPTE ST 2042-1 (VC-2) standards documents.
Home-page: https://github.com/bbc/vc2_pseudocode_parser
Author: BBC R&D
License: GPL-3.0-only
Keywords: vc2 dirac dirac-pro pseudocode parser ast
Platform: UNKNOWN
Classifier: Development Status :: 3 - Alpha
Classifier: Intended Audience :: Developers
Classifier: License :: OSI Approved :: GNU General Public License v3 (GPLv3)
Classifier: Operating System :: POSIX :: Linux
Classifier: Operating System :: Microsoft :: Windows
Classifier: Operating System :: MacOS
Classifier: Programming Language :: Python :: 3
Classifier: Programming Language :: Python :: 3 :: Only
Classifier: Programming Language :: Python :: 3.6
Classifier: Programming Language :: Python :: 3.7
Classifier: Programming Language :: Python :: 3.8
Classifier: Programming Language :: Python :: 3.9
Requires-Dist: peggie (>=0.1.1)
Requires-Dist: dataclasses ; python_version < "3.7"
Provides-Extra: docx
Requires-Dist: python-docx (>=0.3.0) ; extra == 'docx'
